f8c/__init__.py
f8c/cli.py
f8c-0.1.2.dist-info/entry_points.txt
f8c-0.1.2.dist-info/LICENSE
f8c-0.1.2.dist-info/WHEEL
f8c-0.1.2.dist-info/METADATA
f8c-0.1.2.dist-info/RECORD
