Metadata-Version: 2.1
Name: f8c
Version: 0.1.2
Summary: cli wrapper around flake8_codes
Home-page: https://pypi.org/project/f8c
Author: Ryan Delaney
Author-email: ryan.patrick.delaney@protonmail.com
Requires-Python: >=3.10,<4.0
Classifier: Programming Language :: Python :: 3
Classifier: Programming Language :: Python :: 3.10
Requires-Dist: click (>=8.0.3,<9.0.0)
Requires-Dist: flake8-codes (>=0.1.1,<0.2.0)
Project-URL: Repository, https://github.com/rpdelaney/f8c
